setup.py
salure_helpers/task_scheduler/__init__.py
salure_helpers/task_scheduler/task_scheduler.py
salure_helpers_task_scheduler.egg-info/PKG-INFO
salure_helpers_task_scheduler.egg-info/SOURCES.txt
salure_helpers_task_scheduler.egg-info/dependency_links.txt
salure_helpers_task_scheduler.egg-info/not-zip-safe
salure_helpers_task_scheduler.egg-info/requires.txt
salure_helpers_task_scheduler.egg-info/top_level.txt