Metadata-Version: 1.0
Name: salure-helpers-task-scheduler
Version: 1.1.0
Summary: Task Scheduler from Salure
Home-page: UNKNOWN
Author: D&A Salure
Author-email: support@salureconnnect.com
License: Salure License
Platform: UNKNOWN
